llm_profile.py
llm_profile-0.6.0.dist-info/licenses/LICENSE
llm_profile-0.6.0.dist-info/METADATA
llm_profile-0.6.0.dist-info/WHEEL
llm_profile-0.6.0.dist-info/entry_points.txt
llm_profile-0.6.0.dist-info/top_level.txt
llm_profile-0.6.0.dist-info/RECORD
