Metadata-Version: 2.4
Name: llm-profile
Version: 0.6.0
Summary: LLM benchmarking tools for the LLM CLI
Author: Anthony Shaw
License: MIT
Project-URL: Homepage, https://github.com/tonybaloney/llm-profile
Project-URL: Changelog, https://github.com/tonybaloney/llm-profile/releases
Project-URL: Issues, https://github.com/tonybaloney/llm-profile/issues
Project-URL: CI, https://github.com/tonybaloney/llm-profile/actions
Classifier: License :: OSI Approved :: MIT License
License-File: LICENSE
Requires-Dist: aiohttp>=3.11.18
Requires-Dist: llm>=0.26
Requires-Dist: rich
Provides-Extra: graph
Requires-Dist: matplotlib; extra == "graph"
Provides-Extra: test
Requires-Dist: pytest; extra == "test"
Requires-Dist: pytest-recording; extra == "test"
Requires-Dist: pytest-asyncio; extra == "test"
Requires-Dist: ruff; extra == "test"
Requires-Dist: pyright; extra == "test"
Dynamic: license-file
